detect_dice/__init__.py
detect_dice/detect_dice.py
detect_dice-1.0.11.dist-info/METADATA
detect_dice-1.0.11.dist-info/WHEEL
detect_dice-1.0.11.dist-info/top_level.txt
detect_dice-1.0.11.dist-info/RECORD
