Metadata-Version: 2.1
Name: detect_dice
Version: 1.0.11
Summary: This package is in the field of image processing and can perform dice detection for you
Home-page: https://github.com/MohamadNematizadeh/detect_dice
Author: MohammadNematizadeh
Author-email: mohammad.nematizzadeh@gmail.com
